hangoutcore/__init__.py
hangoutcore/__main__.py
hangoutcore/bot.py
hangoutcore/setup.py
hangoutcore/util.py
hangoutcore/SystemCogs/development.py
hangoutcore/SystemCogs/economy.py
hangoutcore/SystemCogs/general.py
hangoutcore/SystemCogs/moderation.py
hangoutcore/SystemCogs/music.py
hangoutcore/SystemCogs/system.py
HangoutCore-2.91.5.dist-info/LICENSE
HangoutCore-2.91.5.dist-info/METADATA
HangoutCore-2.91.5.dist-info/WHEEL
HangoutCore-2.91.5.dist-info/entry_points.txt
HangoutCore-2.91.5.dist-info/top_level.txt
HangoutCore-2.91.5.dist-info/RECORD
