Metadata-Version: 2.1
Name: HangoutCore
Version: 2.91.5
Summary: A modular bot for teaching new developers
Home-page: https://github.com/NextYearStudios/HangoutCore
License: GPL-3.0
Requires-Python: >=3.10.6
License-File: LICENSE
Requires-Dist: aiofiles
Requires-Dist: aiohttp
Requires-Dist: async-timeout
Requires-Dist: asyncio-dgram
Requires-Dist: attrs
Requires-Dist: beautifulsoup4
Requires-Dist: certifi
Requires-Dist: cffi
Requires-Dist: chardet
Requires-Dist: charset-normalizer
Requires-Dist: click
Requires-Dist: colorama
Requires-Dist: commonmark
Requires-Dist: discord.py[voice]
Requires-Dist: dnspython
Requires-Dist: ffmpeg-python
Requires-Dist: future
Requires-Dist: idna
Requires-Dist: jproperties
Requires-Dist: mcstatus
Requires-Dist: multidict
Requires-Dist: mutagen
Requires-Dist: pycparser
Requires-Dist: Pygments
Requires-Dist: PyNaCl
Requires-Dist: pytube
Requires-Dist: pytz
Requires-Dist: rapidfuzz
Requires-Dist: requests
Requires-Dist: rich
Requires-Dist: six
Requires-Dist: soupsieve
Requires-Dist: spotdl
Requires-Dist: spotipy
Requires-Dist: tqdm
Requires-Dist: typing-extensions
Requires-Dist: Unidecode
Requires-Dist: urllib3
Requires-Dist: yarl
Requires-Dist: youtube-dl
Requires-Dist: youtube-search
Requires-Dist: ytmusicapi
